reducto/__init__.py
reducto/_base_client.py
reducto/_client.py
reducto/_compat.py
reducto/_constants.py
reducto/_exceptions.py
reducto/_files.py
reducto/_models.py
reducto/_qs.py
reducto/_resource.py
reducto/_response.py
reducto/_streaming.py
reducto/_types.py
reducto/_version.py
reducto/py.typed
reducto/_utils/__init__.py
reducto/_utils/_compat.py
reducto/_utils/_datetime_parse.py
reducto/_utils/_logs.py
reducto/_utils/_proxy.py
reducto/_utils/_reflection.py
reducto/_utils/_resources_proxy.py
reducto/_utils/_streams.py
reducto/_utils/_sync.py
reducto/_utils/_transform.py
reducto/_utils/_typing.py
reducto/_utils/_utils.py
reducto/lib/.keep
reducto/lib/__init__.py
reducto/lib/citations.py
reducto/lib/helpers.py
reducto/resources/__init__.py
reducto/resources/edit.py
reducto/resources/extract.py
reducto/resources/job.py
reducto/resources/parse.py
reducto/resources/pipeline.py
reducto/resources/split.py
reducto/resources/webhook.py
reducto/types/__init__.py
reducto/types/client_upload_params.py
reducto/types/edit_run_job_params.py
reducto/types/edit_run_job_response.py
reducto/types/edit_run_params.py
reducto/types/extract_run_job_params.py
reducto/types/extract_run_job_response.py
reducto/types/extract_run_params.py
reducto/types/extract_run_response.py
reducto/types/job_get_all_params.py
reducto/types/job_get_all_response.py
reducto/types/job_get_response.py
reducto/types/parse_run_job_params.py
reducto/types/parse_run_job_response.py
reducto/types/parse_run_params.py
reducto/types/parse_run_response.py
reducto/types/pipeline_run_job_params.py
reducto/types/pipeline_run_job_response.py
reducto/types/pipeline_run_params.py
reducto/types/split_run_job_params.py
reducto/types/split_run_job_response.py
reducto/types/split_run_params.py
reducto/types/webhook_run_response.py
reducto/types/shared/__init__.py
reducto/types/shared/advanced_citations_config.py
reducto/types/shared/advanced_processing_options.py
reducto/types/shared/array_extract_config.py
reductoai-0.16.0.dist-info/METADATA
reductoai-0.16.0.dist-info/WHEEL
reductoai-0.16.0.dist-info/licenses/LICENSE
reductoai-0.16.0.dist-info/RECORD
